symexpress3/__init__.py
symexpress3/__main__.py
symexpress3/optFunctionBase.py
symexpress3/optTypeBase.py
symexpress3/primefactor.py
symexpress3/symexp3cmd.py
symexpress3/symexpress3.py
symexpress3/symtables.py
symexpress3/symtools.py
symexpress3/version.py
symexpress3/optSymAny/optSymAnyArrayPower.py
symexpress3/optSymAny/optSymAnyExpandArray.py
symexpress3/optSymAny/optSymAnyRootToPrincipalRoot.py
symexpress3/optSymAny/symRegisterOptSymAny.py
symexpress3/optSymFunction/__init__.py
symexpress3/optSymFunction/optSymFunctionAcosToSum.py
symexpress3/optSymFunction/optSymFunctionAsinToSum.py
symexpress3/optSymFunction/optSymFunctionCosAtanDiv3.py
symexpress3/optSymFunction/optSymFunctionCosAtanDivNToSinICos.py
symexpress3/optSymFunction/optSymFunctionCosToE.py
symexpress3/optSymFunction/optSymFunctionCosToSum.py
symexpress3/optSymFunction/optSymFunctionCosXplusYtoSinCos.py
symexpress3/optSymFunction/optSymFunctionEToCosSin.py
symexpress3/optSymFunction/optSymFunctionEToSum.py
symexpress3/optSymFunction/optSymFunctionNumberToDivisors.py
symexpress3/optSymFunction/optSymFunctionNumberToPrimeFactors.py
symexpress3/optSymFunction/optSymFunctionSinAtanDivNToSinICos.py
symexpress3/optSymFunction/optSymFunctionSinToE.py
symexpress3/optSymFunction/optSymFunctionSinToSum.py
symexpress3/optSymFunction/optSymFunctionSinXplusYtoSinCos.py
symexpress3/optSymFunction/symRegisterOptSymFunction.py
symexpress3/optSymNumber/__init__.py
symexpress3/optSymNumber/optSymNumberNegRootToI.py
symexpress3/optSymNumber/optSymNumberOnlyOneRoot.py
symexpress3/optSymNumber/optSymNumberPower.py
symexpress3/optSymNumber/optSymNumberRadicalDenominatorToCounter.py
symexpress3/optSymNumber/symRegisterOptSymNumber.py
symexpress3/optSymVariable/__init__.py
symexpress3/optSymVariable/optSymVariableI.py
symexpress3/optSymVariable/optSymVariableInfinity.py
symexpress3/optSymVariable/optSymVariableRootIToSinCos.py
symexpress3/optSymVariable/symRegisterOptSymVariable.py
symexpress3/optimize/__init__.py
symexpress3-0.0.12.dist-info/METADATA
symexpress3-0.0.12.dist-info/WHEEL
symexpress3-0.0.12.dist-info/licenses/LICENSE
symexpress3-0.0.12.dist-info/RECORD
