Metadata-Version: 2.4
Name: symexpress3
Version: 0.0.12
Summary: A Python module for symbolic calculations
Project-URL: Homepage, https://github.com/SWVandenEnden/
Project-URL: Repository, https://github.com/SWVandenEnden/symexpress3
Author: Gien van den Enden
Author-email: swvandenenden@gmail.com
Maintainer-email: Gien van den Enden <swvandenenden@gmail.com>
License: GNU General Public License v3 or later (GPLv3+)
License-File: LICENSE
Keywords: calculator,math,symbolic
Classifier: Development Status :: 4 - Beta
Classifier: Intended Audience :: Developers
Classifier: Intended Audience :: Education
Classifier: Intended Audience :: Science/Research
Classifier: Operating System :: OS Independent
Classifier: Programming Language :: Python :: 3
Classifier: Topic :: Scientific/Engineering :: Mathematics
Requires-Python: >=3.11
Requires-Dist: mpmath>=1.3.0
Requires-Dist: sympy>=1.13.2
